{
    "pageNumber": 143,
    "data": [
        {
            "id": "109980726",
            "title": "SKIP*HOP&reg; Onyx Tile Grab &amp; Go Double Bottle Bag",
            "date_created": "1502521038",
            "loginId": "1758166",
            "tags": "",
            "description": "",
            "asset": {
                "user": "",
                "videoMeta": {
                    "duration": "22",
                    "width": 1280,
                    "height": 720
                },
                "mediaDuration": "22",
                "prettyDuration": "00:00:22",
                "thumbnailUrl": "\/\/v.tvpage.com\/1758166\/109980726\/84c68\/thumb-d3734f7b0e7e3576844dcb45c4506fa3-00001.jpg",
                "type": "mp4",
                "dashUrl": "\/\/v.tvpage.com\/1758166\/109980726\/84c68\/media.mpd",
                "hlsUrl": "\/\/v.tvpage.com\/1758166\/109980726\/84c68\/media.m3u8",
                "uploadAsset": false,
                "quality": "",
                "sources": [
                    {
                        "file": "\/\/v.tvpage.com\/1758166\/109980726\/84c68\/1080p_media.mp4",
                        "quality": "1080p",
                        "mime": "video\/mp4",
                        "width": 1280,
                        "height": 720
                    },
                    {
                        "file": "\/\/v.tvpage.com\/1758166\/109980726\/84c68\/720p_media.mp4",
                        "quality": "720p",
                        "mime": "video\/mp4",
                        "width": 1280,
                        "height": 720
                    },
                    {
                        "file": "\/\/v.tvpage.com\/1758166\/109980726\/84c68\/480p_media.mp4",
                        "quality": "480p",
                        "mime": "video\/mp4",
                        "width": 854,
                        "height": 480
                    },
                    {
                        "file": "\/\/v.tvpage.com\/1758166\/109980726\/84c68\/360p_media.mp4",
                        "quality": "360p",
                        "mime": "video\/mp4",
                        "width": 640,
                        "height": 360
                    },
                    {
                        "file": "\/\/v.tvpage.com\/1758166\/109980726\/84c68\/240p_media.mp4",
                        "quality": "240p",
                        "mime": "video\/mp4",
                        "width": 320,
                        "height": 180
                    }
                ]
            },
            "parentId": "111091684",
            "url": "\/bbbusa-latest-videos\/skip-hop\u00c2-onyx-tile-grab-go-double-bottle-bag\/111091684-109980726"
        },
        {
            "id": "109980725",
            "title": "18762834536005525.mov",
            "date_created": "1502521037",
            "loginId": "1758166",
            "tags": "",
            "description": "",
            "asset": {
                "user": "",
                "videoMeta": {
                    "duration": "57",
                    "width": 640,
                    "height": 360
                },
                "mediaDuration": "57",
                "prettyDuration": "00:00:57",
                "thumbnailUrl": "\/\/v.tvpage.com\/1758166\/109980725\/85188\/thumb-2dee2f591443bb77e29e06fba8f7ed4d-00001.jpg",
                "type": "mp4",
                "dashUrl": "\/\/v.tvpage.com\/1758166\/109980725\/85188\/media.mpd",
                "hlsUrl": "\/\/v.tvpage.com\/1758166\/109980725\/85188\/media.m3u8",
                "uploadAsset": false,
                "quality": "",
                "sources": [
                    {
                        "file": "\/\/v.tvpage.com\/1758166\/109980725\/85188\/1080p_media.mp4",
                        "quality": "1080p",
                        "mime": "video\/mp4",
                        "width": 640,
                        "height": 360
                    },
                    {
                        "file": "\/\/v.tvpage.com\/1758166\/109980725\/85188\/720p_media.mp4",
                        "quality": "720p",
                        "mime": "video\/mp4",
                        "width": 640,
                        "height": 360
                    },
                    {
                        "file": "\/\/v.tvpage.com\/1758166\/109980725\/85188\/480p_media.mp4",
                        "quality": "480p",
                        "mime": "video\/mp4",
                        "width": 640,
                        "height": 360
                    },
                    {
                        "file": "\/\/v.tvpage.com\/1758166\/109980725\/85188\/360p_media.mp4",
                        "quality": "360p",
                        "mime": "video\/mp4",
                        "width": 640,
                        "height": 360
                    },
                    {
                        "file": "\/\/v.tvpage.com\/1758166\/109980725\/85188\/240p_media.mp4",
                        "quality": "240p",
                        "mime": "video\/mp4",
                        "width": 320,
                        "height": 180
                    }
                ]
            },
            "parentId": "111091684",
            "url": "\/bbbusa-latest-videos\/18762834536005525-mov\/111091684-109980725"
        },
        {
            "id": "109980724",
            "title": "Slouchback comfortable dorm room furniture",
            "date_created": "1502521034",
            "loginId": "1758166",
            "tags": "",
            "description": "",
            "asset": {
                "user": "",
                "videoMeta": {
                    "duration": "44",
                    "width": 1280,
                    "height": 720
                },
                "mediaDuration": "44",
                "prettyDuration": "00:00:44",
                "thumbnailUrl": "\/\/v.tvpage.com\/1758166\/109980724\/909dd\/thumb-1a7c26e06d74afea0605811f8c2676e4-00001.jpg",
                "type": "mp4",
                "dashUrl": "\/\/v.tvpage.com\/1758166\/109980724\/909dd\/media.mpd",
                "hlsUrl": "\/\/v.tvpage.com\/1758166\/109980724\/909dd\/media.m3u8",
                "uploadAsset": false,
                "quality": "",
                "sources": [
                    {
                        "file": "\/\/v.tvpage.com\/1758166\/109980724\/909dd\/1080p_media.mp4",
                        "quality": "1080p",
                        "mime": "video\/mp4",
                        "width": 1280,
                        "height": 720
                    },
                    {
                        "file": "\/\/v.tvpage.com\/1758166\/109980724\/909dd\/720p_media.mp4",
                        "quality": "720p",
                        "mime": "video\/mp4",
                        "width": 1280,
                        "height": 720
                    },
                    {
                        "file": "\/\/v.tvpage.com\/1758166\/109980724\/909dd\/480p_media.mp4",
                        "quality": "480p",
                        "mime": "video\/mp4",
                        "width": 854,
                        "height": 480
                    },
                    {
                        "file": "\/\/v.tvpage.com\/1758166\/109980724\/909dd\/360p_media.mp4",
                        "quality": "360p",
                        "mime": "video\/mp4",
                        "width": 640,
                        "height": 360
                    },
                    {
                        "file": "\/\/v.tvpage.com\/1758166\/109980724\/909dd\/240p_media.mp4",
                        "quality": "240p",
                        "mime": "video\/mp4",
                        "width": 320,
                        "height": 180
                    }
                ]
            },
            "parentId": "111091684",
            "url": "\/bbbusa-latest-videos\/slouchback-comfortable-dorm-room-furniture\/111091684-109980724"
        },
        {
            "id": "109980723",
            "title": "Drop Scale Smart Kitchen Scale and Recipe App",
            "date_created": "1502521030",
            "loginId": "1758166",
            "tags": "",
            "description": "",
            "asset": {
                "user": "",
                "videoMeta": {
                    "duration": "75",
                    "width": 1280,
                    "height": 720
                },
                "mediaDuration": "75",
                "prettyDuration": "00:01:15",
                "thumbnailUrl": "\/\/v.tvpage.com\/1758166\/109980723\/d173b\/thumb-56000f3e3b927ccb87baa19cafabc666-00002.jpg",
                "type": "mp4",
                "dashUrl": "\/\/v.tvpage.com\/1758166\/109980723\/d173b\/media.mpd",
                "hlsUrl": "\/\/v.tvpage.com\/1758166\/109980723\/d173b\/media.m3u8",
                "uploadAsset": false,
                "quality": "",
                "sources": [
                    {
                        "file": "\/\/v.tvpage.com\/1758166\/109980723\/d173b\/1080p_media.mp4",
                        "quality": "1080p",
                        "mime": "video\/mp4",
                        "width": 1280,
                        "height": 720
                    },
                    {
                        "file": "\/\/v.tvpage.com\/1758166\/109980723\/d173b\/720p_media.mp4",
                        "quality": "720p",
                        "mime": "video\/mp4",
                        "width": 1280,
                        "height": 720
                    },
                    {
                        "file": "\/\/v.tvpage.com\/1758166\/109980723\/d173b\/480p_media.mp4",
                        "quality": "480p",
                        "mime": "video\/mp4",
                        "width": 854,
                        "height": 480
                    },
                    {
                        "file": "\/\/v.tvpage.com\/1758166\/109980723\/d173b\/360p_media.mp4",
                        "quality": "360p",
                        "mime": "video\/mp4",
                        "width": 640,
                        "height": 360
                    },
                    {
                        "file": "\/\/v.tvpage.com\/1758166\/109980723\/d173b\/240p_media.mp4",
                        "quality": "240p",
                        "mime": "video\/mp4",
                        "width": 320,
                        "height": 180
                    }
                ]
            },
            "parentId": "111091684",
            "url": "\/bbbusa-latest-videos\/drop-scale-smart-kitchen-scale-and-recipe-app-3-notes\/111091684-109980723"
        },
        {
            "id": "109980722",
            "title": "Graco&reg; Size4Me&trade; 65 Convertible Car Seat",
            "date_created": "1502521028",
            "loginId": "1758166",
            "tags": "",
            "description": "",
            "asset": {
                "user": "",
                "videoMeta": {
                    "duration": "98",
                    "width": 1280,
                    "height": 720
                },
                "mediaDuration": "98",
                "prettyDuration": "00:01:38",
                "thumbnailUrl": "\/\/v.tvpage.com\/1758166\/109980722\/1a472\/thumb-1ab5476780e2ef4ef91e78cfeacec203-00002.jpg",
                "type": "mp4",
                "dashUrl": "\/\/v.tvpage.com\/1758166\/109980722\/1a472\/media.mpd",
                "hlsUrl": "\/\/v.tvpage.com\/1758166\/109980722\/1a472\/media.m3u8",
                "uploadAsset": false,
                "quality": "",
                "sources": [
                    {
                        "file": "\/\/v.tvpage.com\/1758166\/109980722\/1a472\/1080p_media.mp4",
                        "quality": "1080p",
                        "mime": "video\/mp4",
                        "width": 1280,
                        "height": 720
                    },
                    {
                        "file": "\/\/v.tvpage.com\/1758166\/109980722\/1a472\/720p_media.mp4",
                        "quality": "720p",
                        "mime": "video\/mp4",
                        "width": 1280,
                        "height": 720
                    },
                    {
                        "file": "\/\/v.tvpage.com\/1758166\/109980722\/1a472\/480p_media.mp4",
                        "quality": "480p",
                        "mime": "video\/mp4",
                        "width": 854,
                        "height": 480
                    },
                    {
                        "file": "\/\/v.tvpage.com\/1758166\/109980722\/1a472\/360p_media.mp4",
                        "quality": "360p",
                        "mime": "video\/mp4",
                        "width": 640,
                        "height": 360
                    },
                    {
                        "file": "\/\/v.tvpage.com\/1758166\/109980722\/1a472\/240p_media.mp4",
                        "quality": "240p",
                        "mime": "video\/mp4",
                        "width": 320,
                        "height": 180
                    }
                ]
            },
            "parentId": "111091684",
            "url": "\/bbbusa-latest-videos\/graco\u00c2-size4me\u00e2-65-convertible-car-seat\/111091684-109980722"
        },
        {
            "id": "109980721",
            "title": "Baby Jogger&reg; Summit&trade; X3 Single Stroller",
            "date_created": "1502521026",
            "loginId": "1758166",
            "tags": "",
            "description": "",
            "asset": {
                "user": "",
                "videoMeta": {
                    "duration": "114",
                    "width": 1280,
                    "height": 720
                },
                "mediaDuration": "114",
                "prettyDuration": "00:01:54",
                "thumbnailUrl": "\/\/v.tvpage.com\/1758166\/109980721\/fad81\/thumb-3725c0d3273ad29e394926397423b372-00002.jpg",
                "type": "mp4",
                "dashUrl": "\/\/v.tvpage.com\/1758166\/109980721\/fad81\/media.mpd",
                "hlsUrl": "\/\/v.tvpage.com\/1758166\/109980721\/fad81\/media.m3u8",
                "uploadAsset": false,
                "quality": "",
                "sources": [
                    {
                        "file": "\/\/v.tvpage.com\/1758166\/109980721\/fad81\/1080p_media.mp4",
                        "quality": "1080p",
                        "mime": "video\/mp4",
                        "width": 1280,
                        "height": 720
                    },
                    {
                        "file": "\/\/v.tvpage.com\/1758166\/109980721\/fad81\/720p_media.mp4",
                        "quality": "720p",
                        "mime": "video\/mp4",
                        "width": 1280,
                        "height": 720
                    },
                    {
                        "file": "\/\/v.tvpage.com\/1758166\/109980721\/fad81\/480p_media.mp4",
                        "quality": "480p",
                        "mime": "video\/mp4",
                        "width": 854,
                        "height": 480
                    },
                    {
                        "file": "\/\/v.tvpage.com\/1758166\/109980721\/fad81\/360p_media.mp4",
                        "quality": "360p",
                        "mime": "video\/mp4",
                        "width": 640,
                        "height": 360
                    },
                    {
                        "file": "\/\/v.tvpage.com\/1758166\/109980721\/fad81\/240p_media.mp4",
                        "quality": "240p",
                        "mime": "video\/mp4",
                        "width": 320,
                        "height": 180
                    }
                ]
            },
            "parentId": "111091684",
            "url": "\/bbbusa-latest-videos\/baby-jogger\u00c2-summit\u00e2-x3-single-stroller\/111091684-109980721"
        },
        {
            "id": "109980720",
            "title": "Samsung SimpleVIEW Video Baby Monitor with 4.3-Inch Color LCD Screen",
            "date_created": "1502521023",
            "loginId": "1758166",
            "tags": "",
            "description": "",
            "asset": {
                "user": "",
                "videoMeta": {
                    "duration": "111",
                    "width": 1920,
                    "height": 1080
                },
                "mediaDuration": "111",
                "prettyDuration": "00:01:51",
                "thumbnailUrl": "\/\/v.tvpage.com\/1758166\/109980720\/bb867\/thumb-c0a64ff2fe4f408f009891a2488cae40-00002.jpg",
                "type": "mp4",
                "dashUrl": "\/\/v.tvpage.com\/1758166\/109980720\/bb867\/media.mpd",
                "hlsUrl": "\/\/v.tvpage.com\/1758166\/109980720\/bb867\/media.m3u8",
                "uploadAsset": false,
                "quality": "",
                "sources": [
                    {
                        "file": "\/\/v.tvpage.com\/1758166\/109980720\/bb867\/1080p_media.mp4",
                        "quality": "1080p",
                        "mime": "video\/mp4",
                        "width": 1920,
                        "height": 1080
                    },
                    {
                        "file": "\/\/v.tvpage.com\/1758166\/109980720\/bb867\/720p_media.mp4",
                        "quality": "720p",
                        "mime": "video\/mp4",
                        "width": 1280,
                        "height": 720
                    },
                    {
                        "file": "\/\/v.tvpage.com\/1758166\/109980720\/bb867\/480p_media.mp4",
                        "quality": "480p",
                        "mime": "video\/mp4",
                        "width": 854,
                        "height": 480
                    },
                    {
                        "file": "\/\/v.tvpage.com\/1758166\/109980720\/bb867\/360p_media.mp4",
                        "quality": "360p",
                        "mime": "video\/mp4",
                        "width": 640,
                        "height": 360
                    },
                    {
                        "file": "\/\/v.tvpage.com\/1758166\/109980720\/bb867\/240p_media.mp4",
                        "quality": "240p",
                        "mime": "video\/mp4",
                        "width": 320,
                        "height": 180
                    }
                ]
            },
            "parentId": "111091684",
            "url": "\/bbbusa-latest-videos\/samsung-simpleview-video-baby-monitor-with-4-3-inch-colo-4-notes\/111091684-109980720"
        },
        {
            "id": "109980719",
            "title": "Gripper Window Tension Rod",
            "date_created": "1502521021",
            "loginId": "1758166",
            "tags": "",
            "description": "",
            "asset": {
                "user": "",
                "videoMeta": {
                    "duration": "37",
                    "width": 512,
                    "height": 288
                },
                "mediaDuration": "37",
                "prettyDuration": "00:00:37",
                "thumbnailUrl": "\/\/v.tvpage.com\/1758166\/109980719\/feb62\/thumb-4a3a345a16743a1faf799b50a83bae9c-00001.jpg",
                "type": "mp4",
                "dashUrl": "\/\/v.tvpage.com\/1758166\/109980719\/feb62\/media.mpd",
                "hlsUrl": "\/\/v.tvpage.com\/1758166\/109980719\/feb62\/media.m3u8",
                "uploadAsset": false,
                "quality": "",
                "sources": [
                    {
                        "file": "\/\/v.tvpage.com\/1758166\/109980719\/feb62\/1080p_media.mp4",
                        "quality": "1080p",
                        "mime": "video\/mp4",
                        "width": 512,
                        "height": 288
                    },
                    {
                        "file": "\/\/v.tvpage.com\/1758166\/109980719\/feb62\/720p_media.mp4",
                        "quality": "720p",
                        "mime": "video\/mp4",
                        "width": 512,
                        "height": 288
                    },
                    {
                        "file": "\/\/v.tvpage.com\/1758166\/109980719\/feb62\/480p_media.mp4",
                        "quality": "480p",
                        "mime": "video\/mp4",
                        "width": 512,
                        "height": 288
                    },
                    {
                        "file": "\/\/v.tvpage.com\/1758166\/109980719\/feb62\/360p_media.mp4",
                        "quality": "360p",
                        "mime": "video\/mp4",
                        "width": 512,
                        "height": 288
                    },
                    {
                        "file": "\/\/v.tvpage.com\/1758166\/109980719\/feb62\/240p_media.mp4",
                        "quality": "240p",
                        "mime": "video\/mp4",
                        "width": 320,
                        "height": 180
                    }
                ]
            },
            "parentId": "111091684",
            "url": "\/bbbusa-latest-videos\/gripper-window-tension-rod-2-notes\/111091684-109980719"
        },
        {
            "id": "109980718",
            "title": "InStyler BLU Turbo Ionic Dryer",
            "date_created": "1502521019",
            "loginId": "1758166",
            "tags": "",
            "description": "",
            "asset": {
                "user": "",
                "videoMeta": {
                    "duration": "33",
                    "width": 1920,
                    "height": 1080
                },
                "mediaDuration": "33",
                "prettyDuration": "00:00:33",
                "thumbnailUrl": "\/\/v.tvpage.com\/1758166\/109980718\/b5342\/thumb-750bf9fa1f36789e5209fc89a3ed2b33-00001.jpg",
                "type": "mp4",
                "dashUrl": "\/\/v.tvpage.com\/1758166\/109980718\/b5342\/media.mpd",
                "hlsUrl": "\/\/v.tvpage.com\/1758166\/109980718\/b5342\/media.m3u8",
                "uploadAsset": false,
                "quality": "",
                "sources": [
                    {
                        "file": "\/\/v.tvpage.com\/1758166\/109980718\/b5342\/1080p_media.mp4",
                        "quality": "1080p",
                        "mime": "video\/mp4",
                        "width": 1920,
                        "height": 1080
                    },
                    {
                        "file": "\/\/v.tvpage.com\/1758166\/109980718\/b5342\/720p_media.mp4",
                        "quality": "720p",
                        "mime": "video\/mp4",
                        "width": 1280,
                        "height": 720
                    },
                    {
                        "file": "\/\/v.tvpage.com\/1758166\/109980718\/b5342\/480p_media.mp4",
                        "quality": "480p",
                        "mime": "video\/mp4",
                        "width": 854,
                        "height": 480
                    },
                    {
                        "file": "\/\/v.tvpage.com\/1758166\/109980718\/b5342\/360p_media.mp4",
                        "quality": "360p",
                        "mime": "video\/mp4",
                        "width": 640,
                        "height": 360
                    },
                    {
                        "file": "\/\/v.tvpage.com\/1758166\/109980718\/b5342\/240p_media.mp4",
                        "quality": "240p",
                        "mime": "video\/mp4",
                        "width": 320,
                        "height": 180
                    }
                ]
            },
            "parentId": "111091684",
            "url": "\/bbbusa-latest-videos\/instyler-blu-turbo-ionic-dryer-3-notes\/111091684-109980718"
        },
        {
            "id": "109980717",
            "title": "iRobot&reg;  Mirra 530 Pool Cleaning Robot",
            "date_created": "1502521012",
            "loginId": "1758166",
            "tags": "",
            "description": "",
            "asset": {
                "user": "",
                "videoMeta": {
                    "duration": "152",
                    "width": 1280,
                    "height": 720
                },
                "mediaDuration": "152",
                "prettyDuration": "00:02:32",
                "thumbnailUrl": "\/\/v.tvpage.com\/1758166\/109980717\/f8490\/thumb-88543c5430b54d8e354b5e1ff2f6a8d6-00002.jpg",
                "type": "mp4",
                "dashUrl": "\/\/v.tvpage.com\/1758166\/109980717\/f8490\/media.mpd",
                "hlsUrl": "\/\/v.tvpage.com\/1758166\/109980717\/f8490\/media.m3u8",
                "uploadAsset": false,
                "quality": "",
                "sources": [
                    {
                        "file": "\/\/v.tvpage.com\/1758166\/109980717\/f8490\/1080p_media.mp4",
                        "quality": "1080p",
                        "mime": "video\/mp4",
                        "width": 1280,
                        "height": 720
                    },
                    {
                        "file": "\/\/v.tvpage.com\/1758166\/109980717\/f8490\/720p_media.mp4",
                        "quality": "720p",
                        "mime": "video\/mp4",
                        "width": 1280,
                        "height": 720
                    },
                    {
                        "file": "\/\/v.tvpage.com\/1758166\/109980717\/f8490\/480p_media.mp4",
                        "quality": "480p",
                        "mime": "video\/mp4",
                        "width": 854,
                        "height": 480
                    },
                    {
                        "file": "\/\/v.tvpage.com\/1758166\/109980717\/f8490\/360p_media.mp4",
                        "quality": "360p",
                        "mime": "video\/mp4",
                        "width": 640,
                        "height": 360
                    },
                    {
                        "file": "\/\/v.tvpage.com\/1758166\/109980717\/f8490\/240p_media.mp4",
                        "quality": "240p",
                        "mime": "video\/mp4",
                        "width": 320,
                        "height": 180
                    }
                ]
            },
            "parentId": "111091684",
            "url": "\/bbbusa-latest-videos\/irobot\u00c2-mirra-530-pool-cleaning-robot-2-notes\/111091684-109980717"
        },
        {
            "id": "109980716",
            "title": "Squish Collapsible Splatter Shield",
            "date_created": "1502521009",
            "loginId": "1758166",
            "tags": "",
            "description": "",
            "asset": {
                "user": "",
                "videoMeta": {
                    "duration": "42",
                    "width": 640,
                    "height": 360
                },
                "mediaDuration": "42",
                "prettyDuration": "00:00:42",
                "thumbnailUrl": "\/\/v.tvpage.com\/1758166\/109980716\/0d739\/thumb-1f3b8412a32c6ac3189cdefa630340ae-00001.jpg",
                "type": "mp4",
                "dashUrl": "\/\/v.tvpage.com\/1758166\/109980716\/0d739\/media.mpd",
                "hlsUrl": "\/\/v.tvpage.com\/1758166\/109980716\/0d739\/media.m3u8",
                "uploadAsset": false,
                "quality": "",
                "sources": [
                    {
                        "file": "\/\/v.tvpage.com\/1758166\/109980716\/0d739\/1080p_media.mp4",
                        "quality": "1080p",
                        "mime": "video\/mp4",
                        "width": 640,
                        "height": 360
                    },
                    {
                        "file": "\/\/v.tvpage.com\/1758166\/109980716\/0d739\/720p_media.mp4",
                        "quality": "720p",
                        "mime": "video\/mp4",
                        "width": 640,
                        "height": 360
                    },
                    {
                        "file": "\/\/v.tvpage.com\/1758166\/109980716\/0d739\/480p_media.mp4",
                        "quality": "480p",
                        "mime": "video\/mp4",
                        "width": 640,
                        "height": 360
                    },
                    {
                        "file": "\/\/v.tvpage.com\/1758166\/109980716\/0d739\/360p_media.mp4",
                        "quality": "360p",
                        "mime": "video\/mp4",
                        "width": 640,
                        "height": 360
                    },
                    {
                        "file": "\/\/v.tvpage.com\/1758166\/109980716\/0d739\/240p_media.mp4",
                        "quality": "240p",
                        "mime": "video\/mp4",
                        "width": 320,
                        "height": 180
                    }
                ]
            },
            "parentId": "111091684",
            "url": "\/bbbusa-latest-videos\/squish-collapsible-splatter-shield-3-notes\/111091684-109980716"
        },
        {
            "id": "109980715",
            "title": "Baby K'tan&reg; Baby Carrier",
            "date_created": "1502521008",
            "loginId": "1758166",
            "tags": "",
            "description": "",
            "asset": {
                "user": "",
                "videoMeta": {
                    "duration": "57",
                    "width": 1280,
                    "height": 720
                },
                "mediaDuration": "57",
                "prettyDuration": "00:00:57",
                "thumbnailUrl": "\/\/v.tvpage.com\/1758166\/109980715\/7504a\/thumb-d720b66702e3b3b39c2b48f08410e8b6-00001.jpg",
                "type": "mp4",
                "dashUrl": "\/\/v.tvpage.com\/1758166\/109980715\/7504a\/media.mpd",
                "hlsUrl": "\/\/v.tvpage.com\/1758166\/109980715\/7504a\/media.m3u8",
                "uploadAsset": false,
                "quality": "",
                "sources": [
                    {
                        "file": "\/\/v.tvpage.com\/1758166\/109980715\/7504a\/1080p_media.mp4",
                        "quality": "1080p",
                        "mime": "video\/mp4",
                        "width": 1280,
                        "height": 720
                    },
                    {
                        "file": "\/\/v.tvpage.com\/1758166\/109980715\/7504a\/720p_media.mp4",
                        "quality": "720p",
                        "mime": "video\/mp4",
                        "width": 1280,
                        "height": 720
                    },
                    {
                        "file": "\/\/v.tvpage.com\/1758166\/109980715\/7504a\/480p_media.mp4",
                        "quality": "480p",
                        "mime": "video\/mp4",
                        "width": 854,
                        "height": 480
                    },
                    {
                        "file": "\/\/v.tvpage.com\/1758166\/109980715\/7504a\/360p_media.mp4",
                        "quality": "360p",
                        "mime": "video\/mp4",
                        "width": 640,
                        "height": 360
                    },
                    {
                        "file": "\/\/v.tvpage.com\/1758166\/109980715\/7504a\/240p_media.mp4",
                        "quality": "240p",
                        "mime": "video\/mp4",
                        "width": 320,
                        "height": 180
                    }
                ]
            },
            "parentId": "111091684",
            "url": "\/bbbusa-latest-videos\/baby-k-tan\u00c2-baby-carrier\/111091684-109980715"
        },
        {
            "id": "109980714",
            "title": "Studio 3B 6-Shelf Sweater Organizer",
            "date_created": "1502521006",
            "loginId": "1758166",
            "tags": "",
            "description": "",
            "asset": {
                "user": "",
                "videoMeta": {
                    "duration": "35",
                    "width": 1920,
                    "height": 1080
                },
                "mediaDuration": "35",
                "prettyDuration": "00:00:35",
                "thumbnailUrl": "\/\/v.tvpage.com\/1758166\/109980714\/d764c\/thumb-9399d0c3b08e3468dcc74fb381360b30-00001.jpg",
                "type": "mp4",
                "dashUrl": "\/\/v.tvpage.com\/1758166\/109980714\/d764c\/media.mpd",
                "hlsUrl": "\/\/v.tvpage.com\/1758166\/109980714\/d764c\/media.m3u8",
                "uploadAsset": false,
                "quality": "",
                "sources": [
                    {
                        "file": "\/\/v.tvpage.com\/1758166\/109980714\/d764c\/1080p_media.mp4",
                        "quality": "1080p",
                        "mime": "video\/mp4",
                        "width": 1920,
                        "height": 1080
                    },
                    {
                        "file": "\/\/v.tvpage.com\/1758166\/109980714\/d764c\/720p_media.mp4",
                        "quality": "720p",
                        "mime": "video\/mp4",
                        "width": 1280,
                        "height": 720
                    },
                    {
                        "file": "\/\/v.tvpage.com\/1758166\/109980714\/d764c\/480p_media.mp4",
                        "quality": "480p",
                        "mime": "video\/mp4",
                        "width": 854,
                        "height": 480
                    },
                    {
                        "file": "\/\/v.tvpage.com\/1758166\/109980714\/d764c\/360p_media.mp4",
                        "quality": "360p",
                        "mime": "video\/mp4",
                        "width": 640,
                        "height": 360
                    },
                    {
                        "file": "\/\/v.tvpage.com\/1758166\/109980714\/d764c\/240p_media.mp4",
                        "quality": "240p",
                        "mime": "video\/mp4",
                        "width": 320,
                        "height": 180
                    }
                ]
            },
            "parentId": "111091684",
            "url": "\/bbbusa-latest-videos\/studio-3b-6-shelf-sweater-organizer-2-notes\/111091684-109980714"
        },
        {
            "id": "109980713",
            "title": "Veggetti&reg; Pro Tabletop Spiral Vegetable Cutter",
            "date_created": "1502521004",
            "loginId": "1758166",
            "tags": "",
            "description": "",
            "asset": {
                "user": "",
                "videoMeta": {
                    "duration": "85",
                    "width": 1280,
                    "height": 720
                },
                "mediaDuration": "85",
                "prettyDuration": "00:01:25",
                "thumbnailUrl": "\/\/v.tvpage.com\/1758166\/109980713\/ab0ae\/thumb-c69ccb7102b7de33f1d759b05d4579db-00002.jpg",
                "type": "mp4",
                "dashUrl": "\/\/v.tvpage.com\/1758166\/109980713\/ab0ae\/media.mpd",
                "hlsUrl": "\/\/v.tvpage.com\/1758166\/109980713\/ab0ae\/media.m3u8",
                "uploadAsset": false,
                "quality": "",
                "sources": [
                    {
                        "file": "\/\/v.tvpage.com\/1758166\/109980713\/ab0ae\/1080p_media.mp4",
                        "quality": "1080p",
                        "mime": "video\/mp4",
                        "width": 1280,
                        "height": 720
                    },
                    {
                        "file": "\/\/v.tvpage.com\/1758166\/109980713\/ab0ae\/720p_media.mp4",
                        "quality": "720p",
                        "mime": "video\/mp4",
                        "width": 1280,
                        "height": 720
                    },
                    {
                        "file": "\/\/v.tvpage.com\/1758166\/109980713\/ab0ae\/480p_media.mp4",
                        "quality": "480p",
                        "mime": "video\/mp4",
                        "width": 854,
                        "height": 480
                    },
                    {
                        "file": "\/\/v.tvpage.com\/1758166\/109980713\/ab0ae\/360p_media.mp4",
                        "quality": "360p",
                        "mime": "video\/mp4",
                        "width": 640,
                        "height": 360
                    },
                    {
                        "file": "\/\/v.tvpage.com\/1758166\/109980713\/ab0ae\/240p_media.mp4",
                        "quality": "240p",
                        "mime": "video\/mp4",
                        "width": 320,
                        "height": 180
                    }
                ]
            },
            "parentId": "111091684",
            "url": "\/bbbusa-latest-videos\/veggetti\u00c2-pro-tabletop-spiral-vegetable-cutter-2-notes\/111091684-109980713"
        },
        {
            "id": "109980712",
            "title": "12298wonder skirt how to.mov",
            "date_created": "1502521000",
            "loginId": "1758166",
            "tags": "",
            "description": "",
            "asset": {
                "user": "",
                "videoMeta": {
                    "duration": "95",
                    "width": 1280,
                    "height": 720
                },
                "mediaDuration": "95",
                "prettyDuration": "00:01:35",
                "thumbnailUrl": "\/\/v.tvpage.com\/1758166\/109980712\/bc473\/thumb-e2e8601eb86927475103db58366bc79f-00002.jpg",
                "type": "mp4",
                "dashUrl": "\/\/v.tvpage.com\/1758166\/109980712\/bc473\/media.mpd",
                "hlsUrl": "\/\/v.tvpage.com\/1758166\/109980712\/bc473\/media.m3u8",
                "uploadAsset": false,
                "quality": "",
                "sources": [
                    {
                        "file": "\/\/v.tvpage.com\/1758166\/109980712\/bc473\/1080p_media.mp4",
                        "quality": "1080p",
                        "mime": "video\/mp4",
                        "width": 1280,
                        "height": 720
                    },
                    {
                        "file": "\/\/v.tvpage.com\/1758166\/109980712\/bc473\/720p_media.mp4",
                        "quality": "720p",
                        "mime": "video\/mp4",
                        "width": 1280,
                        "height": 720
                    },
                    {
                        "file": "\/\/v.tvpage.com\/1758166\/109980712\/bc473\/480p_media.mp4",
                        "quality": "480p",
                        "mime": "video\/mp4",
                        "width": 854,
                        "height": 480
                    },
                    {
                        "file": "\/\/v.tvpage.com\/1758166\/109980712\/bc473\/360p_media.mp4",
                        "quality": "360p",
                        "mime": "video\/mp4",
                        "width": 640,
                        "height": 360
                    },
                    {
                        "file": "\/\/v.tvpage.com\/1758166\/109980712\/bc473\/240p_media.mp4",
                        "quality": "240p",
                        "mime": "video\/mp4",
                        "width": 320,
                        "height": 180
                    }
                ]
            },
            "parentId": "111091684",
            "url": "\/bbbusa-latest-videos\/12298wonder-skirt-how-to-mov\/111091684-109980712"
        },
        {
            "id": "109980711",
            "title": "InkIvy",
            "date_created": "1502520997",
            "loginId": "1758166",
            "tags": "",
            "description": "",
            "asset": {
                "user": "",
                "videoMeta": {
                    "duration": "30",
                    "width": 1920,
                    "height": 1080
                },
                "mediaDuration": "30",
                "prettyDuration": "00:00:30",
                "thumbnailUrl": "\/\/v.tvpage.com\/1758166\/109980711\/e39ff\/thumb-eb7667e621d04d866b51ec4b8cca40b2-00001.jpg",
                "type": "mp4",
                "dashUrl": "\/\/v.tvpage.com\/1758166\/109980711\/e39ff\/media.mpd",
                "hlsUrl": "\/\/v.tvpage.com\/1758166\/109980711\/e39ff\/media.m3u8",
                "uploadAsset": false,
                "quality": "",
                "sources": [
                    {
                        "file": "\/\/v.tvpage.com\/1758166\/109980711\/e39ff\/1080p_media.mp4",
                        "quality": "1080p",
                        "mime": "video\/mp4",
                        "width": 1920,
                        "height": 1080
                    },
                    {
                        "file": "\/\/v.tvpage.com\/1758166\/109980711\/e39ff\/720p_media.mp4",
                        "quality": "720p",
                        "mime": "video\/mp4",
                        "width": 1280,
                        "height": 720
                    },
                    {
                        "file": "\/\/v.tvpage.com\/1758166\/109980711\/e39ff\/480p_media.mp4",
                        "quality": "480p",
                        "mime": "video\/mp4",
                        "width": 854,
                        "height": 480
                    },
                    {
                        "file": "\/\/v.tvpage.com\/1758166\/109980711\/e39ff\/360p_media.mp4",
                        "quality": "360p",
                        "mime": "video\/mp4",
                        "width": 640,
                        "height": 360
                    },
                    {
                        "file": "\/\/v.tvpage.com\/1758166\/109980711\/e39ff\/240p_media.mp4",
                        "quality": "240p",
                        "mime": "video\/mp4",
                        "width": 320,
                        "height": 180
                    }
                ]
            },
            "parentId": "111091684",
            "url": "\/bbbusa-latest-videos\/inkivy\/111091684-109980711"
        },
        {
            "id": "109980710",
            "title": "Beautyrest&reg; Silver&trade;  Mattresses",
            "date_created": "1502520995",
            "loginId": "1758166",
            "tags": "",
            "description": "",
            "asset": {
                "user": "",
                "videoMeta": {
                    "duration": "69",
                    "width": 1280,
                    "height": 720
                },
                "mediaDuration": "69",
                "prettyDuration": "00:01:09",
                "thumbnailUrl": "\/\/v.tvpage.com\/1758166\/109980710\/72cb4\/thumb-b8078502753e6377e3a144801faaf5b0-00002.jpg",
                "type": "mp4",
                "dashUrl": "\/\/v.tvpage.com\/1758166\/109980710\/72cb4\/media.mpd",
                "hlsUrl": "\/\/v.tvpage.com\/1758166\/109980710\/72cb4\/media.m3u8",
                "uploadAsset": false,
                "quality": "",
                "sources": [
                    {
                        "file": "\/\/v.tvpage.com\/1758166\/109980710\/72cb4\/1080p_media.mp4",
                        "quality": "1080p",
                        "mime": "video\/mp4",
                        "width": 1280,
                        "height": 720
                    },
                    {
                        "file": "\/\/v.tvpage.com\/1758166\/109980710\/72cb4\/720p_media.mp4",
                        "quality": "720p",
                        "mime": "video\/mp4",
                        "width": 1280,
                        "height": 720
                    },
                    {
                        "file": "\/\/v.tvpage.com\/1758166\/109980710\/72cb4\/480p_media.mp4",
                        "quality": "480p",
                        "mime": "video\/mp4",
                        "width": 854,
                        "height": 480
                    },
                    {
                        "file": "\/\/v.tvpage.com\/1758166\/109980710\/72cb4\/360p_media.mp4",
                        "quality": "360p",
                        "mime": "video\/mp4",
                        "width": 640,
                        "height": 360
                    },
                    {
                        "file": "\/\/v.tvpage.com\/1758166\/109980710\/72cb4\/240p_media.mp4",
                        "quality": "240p",
                        "mime": "video\/mp4",
                        "width": 320,
                        "height": 180
                    }
                ]
            },
            "parentId": "111091684",
            "url": "\/bbbusa-latest-videos\/beautyrest\u00c2-silver\u00e2-mattresses-3-notes\/111091684-109980710"
        },
        {
            "id": "109980709",
            "title": "Conair&reg; Curl Secret&trade; Hair Styler",
            "date_created": "1502520993",
            "loginId": "1758166",
            "tags": "",
            "description": "",
            "asset": {
                "user": "",
                "videoMeta": {
                    "duration": "31",
                    "width": 1280,
                    "height": 720
                },
                "mediaDuration": "31",
                "prettyDuration": "00:00:31",
                "thumbnailUrl": "\/\/v.tvpage.com\/1758166\/109980709\/7d214\/thumb-e6e117c14671d24859a968ae9fec2cf5-00001.jpg",
                "type": "mp4",
                "dashUrl": "\/\/v.tvpage.com\/1758166\/109980709\/7d214\/media.mpd",
                "hlsUrl": "\/\/v.tvpage.com\/1758166\/109980709\/7d214\/media.m3u8",
                "uploadAsset": false,
                "quality": "",
                "sources": [
                    {
                        "file": "\/\/v.tvpage.com\/1758166\/109980709\/7d214\/1080p_media.mp4",
                        "quality": "1080p",
                        "mime": "video\/mp4",
                        "width": 1280,
                        "height": 720
                    },
                    {
                        "file": "\/\/v.tvpage.com\/1758166\/109980709\/7d214\/720p_media.mp4",
                        "quality": "720p",
                        "mime": "video\/mp4",
                        "width": 1280,
                        "height": 720
                    },
                    {
                        "file": "\/\/v.tvpage.com\/1758166\/109980709\/7d214\/480p_media.mp4",
                        "quality": "480p",
                        "mime": "video\/mp4",
                        "width": 854,
                        "height": 480
                    },
                    {
                        "file": "\/\/v.tvpage.com\/1758166\/109980709\/7d214\/360p_media.mp4",
                        "quality": "360p",
                        "mime": "video\/mp4",
                        "width": 640,
                        "height": 360
                    },
                    {
                        "file": "\/\/v.tvpage.com\/1758166\/109980709\/7d214\/240p_media.mp4",
                        "quality": "240p",
                        "mime": "video\/mp4",
                        "width": 320,
                        "height": 180
                    }
                ]
            },
            "parentId": "111091684",
            "url": "\/bbbusa-latest-videos\/conair\u00c2-curl-secret\u00e2-hair-styler-3-notes\/111091684-109980709"
        },
        {
            "id": "109980708",
            "title": "Cuisinart Egg Central Egg Cooker and Poacher",
            "date_created": "1502520992",
            "loginId": "1758166",
            "tags": "",
            "description": "",
            "asset": {
                "user": "",
                "videoMeta": {
                    "duration": "33",
                    "width": 1920,
                    "height": 1080
                },
                "mediaDuration": "33",
                "prettyDuration": "00:00:33",
                "thumbnailUrl": "\/\/v.tvpage.com\/1758166\/109980708\/fb1cf\/thumb-2c1ec3ace80e5a9e8598406542f95031-00001.jpg",
                "type": "mp4",
                "dashUrl": "\/\/v.tvpage.com\/1758166\/109980708\/fb1cf\/media.mpd",
                "hlsUrl": "\/\/v.tvpage.com\/1758166\/109980708\/fb1cf\/media.m3u8",
                "uploadAsset": false,
                "quality": "",
                "sources": [
                    {
                        "file": "\/\/v.tvpage.com\/1758166\/109980708\/fb1cf\/1080p_media.mp4",
                        "quality": "1080p",
                        "mime": "video\/mp4",
                        "width": 1920,
                        "height": 1080
                    },
                    {
                        "file": "\/\/v.tvpage.com\/1758166\/109980708\/fb1cf\/720p_media.mp4",
                        "quality": "720p",
                        "mime": "video\/mp4",
                        "width": 1280,
                        "height": 720
                    },
                    {
                        "file": "\/\/v.tvpage.com\/1758166\/109980708\/fb1cf\/480p_media.mp4",
                        "quality": "480p",
                        "mime": "video\/mp4",
                        "width": 854,
                        "height": 480
                    },
                    {
                        "file": "\/\/v.tvpage.com\/1758166\/109980708\/fb1cf\/360p_media.mp4",
                        "quality": "360p",
                        "mime": "video\/mp4",
                        "width": 640,
                        "height": 360
                    },
                    {
                        "file": "\/\/v.tvpage.com\/1758166\/109980708\/fb1cf\/240p_media.mp4",
                        "quality": "240p",
                        "mime": "video\/mp4",
                        "width": 320,
                        "height": 180
                    }
                ]
            },
            "parentId": "111091684",
            "url": "\/bbbusa-latest-videos\/cuisinart-egg-central-egg-cooker-and-poacher-2-notes\/111091684-109980708"
        },
        {
            "id": "109980707",
            "title": "Drive Medical Raised 5-inch Toilet Seat with Removable Padded Arms",
            "date_created": "1502520988",
            "loginId": "1758166",
            "tags": "",
            "description": "",
            "asset": {
                "user": "",
                "videoMeta": {
                    "duration": "79",
                    "width": 1280,
                    "height": 720
                },
                "mediaDuration": "79",
                "prettyDuration": "00:01:19",
                "thumbnailUrl": "\/\/v.tvpage.com\/1758166\/109980707\/d5831\/thumb-8a034ef638bf0e9cbbf69e600aa65152-00002.jpg",
                "type": "mp4",
                "dashUrl": "\/\/v.tvpage.com\/1758166\/109980707\/d5831\/media.mpd",
                "hlsUrl": "\/\/v.tvpage.com\/1758166\/109980707\/d5831\/media.m3u8",
                "uploadAsset": false,
                "quality": "",
                "sources": [
                    {
                        "file": "\/\/v.tvpage.com\/1758166\/109980707\/d5831\/1080p_media.mp4",
                        "quality": "1080p",
                        "mime": "video\/mp4",
                        "width": 1280,
                        "height": 720
                    },
                    {
                        "file": "\/\/v.tvpage.com\/1758166\/109980707\/d5831\/720p_media.mp4",
                        "quality": "720p",
                        "mime": "video\/mp4",
                        "width": 1280,
                        "height": 720
                    },
                    {
                        "file": "\/\/v.tvpage.com\/1758166\/109980707\/d5831\/480p_media.mp4",
                        "quality": "480p",
                        "mime": "video\/mp4",
                        "width": 854,
                        "height": 480
                    },
                    {
                        "file": "\/\/v.tvpage.com\/1758166\/109980707\/d5831\/360p_media.mp4",
                        "quality": "360p",
                        "mime": "video\/mp4",
                        "width": 640,
                        "height": 360
                    },
                    {
                        "file": "\/\/v.tvpage.com\/1758166\/109980707\/d5831\/240p_media.mp4",
                        "quality": "240p",
                        "mime": "video\/mp4",
                        "width": 320,
                        "height": 180
                    }
                ]
            },
            "parentId": "111091684",
            "url": "\/bbbusa-latest-videos\/drive-medical-raised-5-inch-toilet-seat-with-removable-p-3-notes\/111091684-109980707"
        }
    ]
}