{
    "title": "2016 B-Agile 3 Double Stroller - Features",
    "description": "Lightweight, maneuverable and simple to fold, Britax\u2019s 2016 B-Agile Double Stroller is easy to carry and navigate while you\u2019re out with your children. The B-Agile Double Stroller is lightweight so pushing and carrying are effortless and quick folding is easy and swift. And the stroller is compatible with all Britax infant car seats so you can create your ideal travel system.",
    "referenceId": "1uGKFwupZnE",
    "date_created": "1464014425",
    "date_modified": "1467160303",
    "tags": "",
    "sourceId": "4",
    "VIDEO_LENGTH": "SHORT",
    "video_type": null,
    "status": "approved",
    "visibility": "1",
    "home_page_gallery": null,
    "category_id_1": null,
    "category_id_2": null,
    "category_id_3": null,
    "category_id_4": null,
    "category_id_5": null,
    "Concept": null,
    "mod_request": null,
    "cc_request": null,
    "id": "65882054",
    "loginId": "1758166",
    "entityType": "1",
    "titleTextEncoded": "2016-B-Agile-3-Double-Stroller-Features",
    "category": "",
    "duration": 92,
    "settings": {},
    "asset": {
        "type": "youtube",
        "thumbnailUrl": "https:\/\/i.ytimg.com\/vi\/1uGKFwupZnE\/hqdefault.jpg",
        "uploadDate": 1464014425,
        "videoId": "1uGKFwupZnE",
        "title": "2016 B-Agile 3 Double Stroller - Features",
        "description": "Lightweight, maneuverable and simple to fold, Britax\u2019s 2016 B-Agile Double Stroller is easy to carry and navigate while you\u2019re out with your children. The B-Agile Double Stroller is lightweight so pushing and carrying are effortless and quick folding is easy and swift. And the stroller is compatible with all Britax infant car seats so you can create your ideal travel system.",
        "author": "Britax Child Safety, Inc",
        "mediaDuration": 92,
        "prettyDuration": "00:01:32",
        "views": "40"
    },
    "transcripts": "[MUSIC PLAYING]",
    "VV_VI": "1",
    "CVV_VI": null,
    "engagement_score": 0,
    "conversion_score": null,
    "metrics_statistics": "{\"VV_VI\":{\"lastUpdatedDate\":\"2017-05-24\",\"engagement_score\":{\"lastUpdatedDate\":\"2017-08-23\"}}}",
    "tvp_profiles": [
        "3"
    ],
    "tvp_profiles_manual": null,
    "tvp_profiles_maxscore": 7577.8994,
    "delete": null,
    "notes": null,
    "uploader": null,
    "modified_date": null,
    "created_date": null,
    "creator": null
}