{
    "title": "Ninja Coffee Bar\u2122: Testimonial 3",
    "description": "The Ninja Coffee Bar is the best coffeehouse in town right on your counter top.",
    "referenceId": "zqEtmgvh3MY",
    "date_created": "1442840247",
    "date_modified": "1466458874",
    "tags": "",
    "sourceId": "4",
    "VIDEO_LENGTH": "SHORT",
    "video_type": "Featured",
    "status": "approved",
    "visibility": "1",
    "home_page_gallery": null,
    "category_id_1": null,
    "category_id_2": null,
    "category_id_3": null,
    "category_id_4": null,
    "category_id_5": null,
    "Concept": null,
    "mod_request": null,
    "cc_request": null,
    "id": "66104530",
    "loginId": "1758166",
    "entityType": "1",
    "titleTextEncoded": "Ninja-Coffee-Bar-Testimonial-3",
    "category": "",
    "duration": 12,
    "settings": "",
    "asset": {
        "type": "youtube",
        "thumbnailUrl": "https:\/\/i.ytimg.com\/vi\/zqEtmgvh3MY\/hqdefault.jpg",
        "uploadDate": 1442840247,
        "videoId": "zqEtmgvh3MY",
        "title": "Ninja Coffee Bar\u2122: Testimonial 3",
        "description": "The Ninja Coffee Bar is the best coffeehouse in town right on your counter top.\n\nLearn more about the Ninja Coffee Bar\u2122 at http:\/\/www.ninjacoffeebar.com. \n\nGet recipes for your Ninja Coffee Bar\u2122 at http:\/\/www.ninjakitchen.com\/recipes.",
        "author": "Ninja Coffee Bar",
        "mediaDuration": 12,
        "prettyDuration": "00:00:12",
        "views": "181",
        "uploadAsset": false,
        "quality": ""
    },
    "transcripts": "There is a lot of times that I just chose not to have coffee over ice because I knew it wouldn't turn out good. Now it's something I can look forward to in the afternoon. I've never had iced coffee this good as I do with the coffee ninja bar.",
    "VV_VI": "567",
    "CVV_VI": null,
    "engagement_score": 8,
    "conversion_score": null,
    "metrics_statistics": "{\"VV_VI\":{\"lastUpdatedDate\":\"2017-05-24\",\"engagement_score\":{\"lastUpdatedDate\":\"2017-08-23\"}}}",
    "tvp_profiles": [
        "18"
    ],
    "tvp_profiles_manual": null,
    "tvp_profiles_maxscore": 5819.6743,
    "delete": null,
    "notes": null,
    "uploader": null,
    "modified_date": null,
    "created_date": null,
    "creator": null
}